{
    "swagger": "2.0",
    "info": {
        "description": "API Server for TodoList Application",
        "title": "Todo App API",
        "contact": {},
        "version": "1.0"
    },
    "basePath": "/",
    "paths": {
        "/api/lists": {
            "get": {
                "security": [
                    {
                        "ApiKeyAuth": []
                    }
                ],
                "produces": [
                    "application/json"
                ],
                "tags": [
                    "lists"
                ],
                "summary": "Get all user lists",
                "operationId": "get-lists",
                "responses": {
                    "200": {
                        "description": "lists",
                        "schema": {
                            "$ref": "#/definitions/handler.UserListsResponse"
                        }
                    },
                    "401": {
                        "description": "user is not authorized",
                        "schema": {
                            "$ref": "#/definitions/handler.ErrorResponse"
                        }
                    },
                    "404": {
                        "description": "user not found",
                        "schema": {
                            "$ref": "#/definitions/handler.ErrorResponse"
                        }
                    },
                    "500": {
                        "description": "internal error",
                        "schema": {
                            "$ref": "#/definitions/handler.ErrorResponse"
                        }
                    }
                }
            },
            "post": {
                "security": [
                    {
                        "ApiKeyAuth": []
                    }
                ],
                "consumes": [
                    "application/json"
                ],
                "produces": [
                    "application/json"
                ],
                "tags": [
                    "lists"
                ],
                "summary": "Create list",
                "operationId": "create-list",
                "parameters": [
                    {
                        "description": "list input",
                        "name": "input",
                        "in": "body",
                        "required": true,
                        "schema": {
                            "$ref": "#/definitions/handler.listCreateReq"
                        }
                    }
                ],
                "responses": {
                    "200": {
                        "description": "success list creation",
                        "schema": {
                            "$ref": "#/definitions/handler.ListCreateResponse"
                        }
                    },
                    "400": {
                        "description": "bad input, auth header errors",
                        "schema": {
                            "$ref": "#/definitions/handler.ErrorResponse"
                        }
                    },
                    "401": {
                        "description": "user is not authorized",
                        "schema": {
                            "$ref": "#/definitions/handler.ErrorResponse"
                        }
                    },
                    "404": {
                        "description": "list not found",
                        "schema": {
                            "$ref": "#/definitions/handler.ErrorResponse"
                        }
                    },
                    "500": {
                        "description": "internal error",
                        "schema": {
                            "$ref": "#/definitions/handler.ErrorResponse"
                        }
                    }
                }
            }
        },
        "/api/lists/{list_id}": {
            "get": {
                "security": [
                    {
                        "ApiKeyAuth": []
                    }
                ],
                "produces": [
                    "application/json"
                ],
                "tags": [
                    "lists"
                ],
                "summary": "Get list by id",
                "operationId": "get-list",
                "parameters": [
                    {
                        "type": "integer",
                        "description": "list_id",
                        "name": "list_id",
                        "in": "path",
                        "required": true
                    }
                ],
                "responses": {
                    "200": {
                        "description": "list",
                        "schema": {
                            "$ref": "#/definitions/models.List"
                        }
                    },
                    "400": {
                        "description": "bad input, auth header errors",
                        "schema": {
                            "$ref": "#/definitions/handler.ErrorResponse"
                        }
                    },
                    "401": {
                        "description": "user is not authorized",
                        "schema": {
                            "$ref": "#/definitions/handler.ErrorResponse"
                        }
                    },
                    "404": {
                        "description": "list not found",
                        "schema": {
                            "$ref": "#/definitions/handler.ErrorResponse"
                        }
                    },
                    "500": {
                        "description": "internal error",
                        "schema": {
                            "$ref": "#/definitions/handler.ErrorResponse"
                        }
                    }
                }
            },
            "delete": {
                "security": [
                    {
                        "ApiKeyAuth": []
                    }
                ],
                "produces": [
                    "application/json"
                ],
                "tags": [
                    "lists"
                ],
                "summary": "Delete list by id",
                "operationId": "delete-list",
                "parameters": [
                    {
                        "type": "integer",
                        "description": "list_id",
                        "name": "list_id",
                        "in": "path",
                        "required": true
                    }
                ],
                "responses": {
                    "200": {
                        "description": "success",
                        "schema": {
                            "type": "string"
                        }
                    },
                    "400": {
                        "description": "bad input, auth header errors",
                        "schema": {
                            "$ref": "#/definitions/handler.ErrorResponse"
                        }
                    },
                    "401": {
                        "description": "user is not authorized",
                        "schema": {
                            "$ref": "#/definitions/handler.ErrorResponse"
                        }
                    },
                    "403": {
                        "description": "current user is not admin",
                        "schema": {
                            "$ref": "#/definitions/handler.ErrorResponse"
                        }
                    },
                    "404": {
                        "description": "list not found",
                        "schema": {
                            "$ref": "#/definitions/handler.ErrorResponse"
                        }
                    },
                    "500": {
                        "description": "internal error",
                        "schema": {
                            "$ref": "#/definitions/handler.ErrorResponse"
                        }
                    }
                }
            },
            "patch": {
                "security": [
                    {
                        "ApiKeyAuth": []
                    }
                ],
                "produces": [
                    "application/json"
                ],
                "tags": [
                    "lists"
                ],
                "summary": "Update list by id",
                "operationId": "delete-list",
                "parameters": [
                    {
                        "type": "integer",
                        "description": "list_id",
                        "name": "list_id",
                        "in": "path",
                        "required": true
                    },
                    {
                        "description": "input",
                        "name": "input",
                        "in": "body",
                        "required": true,
                        "schema": {
                            "$ref": "#/definitions/models.UpdateListReq"
                        }
                    }
                ],
                "responses": {
                    "200": {
                        "description": "success",
                        "schema": {
                            "type": "string"
                        }
                    },
                    "400": {
                        "description": "bad input, auth header errors",
                        "schema": {
                            "$ref": "#/definitions/handler.ErrorResponse"
                        }
                    },
                    "401": {
                        "description": "user is not authorized",
                        "schema": {
                            "$ref": "#/definitions/handler.ErrorResponse"
                        }
                    },
                    "403": {
                        "description": "current user is not admin",
                        "schema": {
                            "$ref": "#/definitions/handler.ErrorResponse"
                        }
                    },
                    "404": {
                        "description": "list not found",
                        "schema": {
                            "$ref": "#/definitions/handler.ErrorResponse"
                        }
                    },
                    "500": {
                        "description": "internal error",
                        "schema": {
                            "$ref": "#/definitions/handler.ErrorResponse"
                        }
                    }
                }
            }
        },
        "/api/lists/{list_id}/edit-role": {
            "patch": {
                "security": [
                    {
                        "ApiKeyAuth": []
                    }
                ],
                "consumes": [
                    "application/json"
                ],
                "produces": [
                    "application/json"
                ],
                "tags": [
                    "lists"
                ],
                "summary": "Edit user role for list",
                "operationId": "edit-role",
                "parameters": [
                    {
                        "type": "integer",
                        "description": "list_id",
                        "name": "list_id",
                        "in": "path",
                        "required": true
                    },
                    {
                        "description": "edit-role input",
                        "name": "input",
                        "in": "body",
                        "required": true,
                        "schema": {
                            "$ref": "#/definitions/handler.editRoleReq"
                        }
                    }
                ],
                "responses": {
                    "200": {
                        "description": "success",
                        "schema": {
                            "type": "string"
                        }
                    },
                    "400": {
                        "description": "bad input, auth header errors",
                        "schema": {
                            "$ref": "#/definitions/handler.ErrorResponse"
                        }
                    },
                    "401": {
                        "description": "user is not authorized",
                        "schema": {
                            "$ref": "#/definitions/handler.ErrorResponse"
                        }
                    },
                    "403": {
                        "description": "current user is not admin",
                        "schema": {
                            "$ref": "#/definitions/handler.ErrorResponse"
                        }
                    },
                    "404": {
                        "description": "list not found, user not found",
                        "schema": {
                            "$ref": "#/definitions/handler.ErrorResponse"
                        }
                    },
                    "500": {
                        "description": "internal error",
                        "schema": {
                            "$ref": "#/definitions/handler.ErrorResponse"
                        }
                    }
                }
            }
        },
        "/api/lists/{list_id}/items": {
            "get": {
                "security": [
                    {
                        "ApiKeyAuth": []
                    }
                ],
                "consumes": [
                    "application/json"
                ],
                "produces": [
                    "application/json"
                ],
                "tags": [
                    "items"
                ],
                "summary": "Get items",
                "operationId": "get-items",
                "parameters": [
                    {
                        "type": "integer",
                        "description": "list_id",
                        "name": "list_id",
                        "in": "path",
                        "required": true
                    }
                ],
                "responses": {
                    "200": {
                        "description": "all user items",
                        "schema": {
                            "$ref": "#/definitions/handler.UserItemsResponse"
                        }
                    },
                    "400": {
                        "description": "bad input, auth header errors",
                        "schema": {
                            "$ref": "#/definitions/handler.ErrorResponse"
                        }
                    },
                    "401": {
                        "description": "user is not authorized",
                        "schema": {
                            "$ref": "#/definitions/handler.ErrorResponse"
                        }
                    },
                    "404": {
                        "description": "list not found",
                        "schema": {
                            "$ref": "#/definitions/handler.ErrorResponse"
                        }
                    },
                    "500": {
                        "description": "internal error",
                        "schema": {
                            "$ref": "#/definitions/handler.ErrorResponse"
                        }
                    }
                }
            },
            "post": {
                "security": [
                    {
                        "ApiKeyAuth": []
                    }
                ],
                "consumes": [
                    "application/json"
                ],
                "produces": [
                    "application/json"
                ],
                "tags": [
                    "items"
                ],
                "summary": "Create item",
                "operationId": "create-item",
                "parameters": [
                    {
                        "type": "integer",
                        "description": "list_id",
                        "name": "list_id",
                        "in": "path",
                        "required": true
                    },
                    {
                        "description": "item input",
                        "name": "input",
                        "in": "body",
                        "required": true,
                        "schema": {
                            "$ref": "#/definitions/handler.itemCreateReq"
                        }
                    }
                ],
                "responses": {
                    "200": {
                        "description": "success item creation",
                        "schema": {
                            "$ref": "#/definitions/handler.ItemCreateResponse"
                        }
                    },
                    "400": {
                        "description": "bad input, auth header errors",
                        "schema": {
                            "$ref": "#/definitions/handler.ErrorResponse"
                        }
                    },
                    "401": {
                        "description": "user is not authorized",
                        "schema": {
                            "$ref": "#/definitions/handler.ErrorResponse"
                        }
                    },
                    "404": {
                        "description": "list not found",
                        "schema": {
                            "$ref": "#/definitions/handler.ErrorResponse"
                        }
                    },
                    "500": {
                        "description": "internal error",
                        "schema": {
                            "$ref": "#/definitions/handler.ErrorResponse"
                        }
                    }
                }
            }
        },
        "/api/lists/{list_id}/items/{item_id}": {
            "get": {
                "security": [
                    {
                        "ApiKeyAuth": []
                    }
                ],
                "consumes": [
                    "application/json"
                ],
                "produces": [
                    "application/json"
                ],
                "tags": [
                    "items"
                ],
                "summary": "Get item",
                "operationId": "get-item",
                "parameters": [
                    {
                        "type": "integer",
                        "description": "list_id",
                        "name": "list_id",
                        "in": "path",
                        "required": true
                    },
                    {
                        "type": "integer",
                        "description": "item_id",
                        "name": "item_id",
                        "in": "path",
                        "required": true
                    }
                ],
                "responses": {
                    "200": {
                        "description": "item",
                        "schema": {
                            "$ref": "#/definitions/models.Item"
                        }
                    },
                    "400": {
                        "description": "bad input, auth header errors",
                        "schema": {
                            "$ref": "#/definitions/handler.ErrorResponse"
                        }
                    },
                    "401": {
                        "description": "user is not authorized",
                        "schema": {
                            "$ref": "#/definitions/handler.ErrorResponse"
                        }
                    },
                    "404": {
                        "description": "list not found, item not found",
                        "schema": {
                            "$ref": "#/definitions/handler.ErrorResponse"
                        }
                    },
                    "500": {
                        "description": "internal error",
                        "schema": {
                            "$ref": "#/definitions/handler.ErrorResponse"
                        }
                    }
                }
            },
            "delete": {
                "security": [
                    {
                        "ApiKeyAuth": []
                    }
                ],
                "consumes": [
                    "application/json"
                ],
                "produces": [
                    "application/json"
                ],
                "tags": [
                    "items"
                ],
                "summary": "Delete item",
                "operationId": "delete-item",
                "parameters": [
                    {
                        "type": "integer",
                        "description": "list_id",
                        "name": "list_id",
                        "in": "path",
                        "required": true
                    },
                    {
                        "type": "integer",
                        "description": "item_id",
                        "name": "item_id",
                        "in": "path",
                        "required": true
                    }
                ],
                "responses": {
                    "200": {
                        "description": "success",
                        "schema": {
                            "type": "string"
                        }
                    },
                    "400": {
                        "description": "bad input, auth header errors",
                        "schema": {
                            "$ref": "#/definitions/handler.ErrorResponse"
                        }
                    },
                    "401": {
                        "description": "user is not authorized",
                        "schema": {
                            "$ref": "#/definitions/handler.ErrorResponse"
                        }
                    },
                    "404": {
                        "description": "list not found, item not found",
                        "schema": {
                            "$ref": "#/definitions/handler.ErrorResponse"
                        }
                    },
                    "500": {
                        "description": "internal error",
                        "schema": {
                            "$ref": "#/definitions/handler.ErrorResponse"
                        }
                    }
                }
            },
            "patch": {
                "security": [
                    {
                        "ApiKeyAuth": []
                    }
                ],
                "consumes": [
                    "application/json"
                ],
                "produces": [
                    "application/json"
                ],
                "tags": [
                    "items"
                ],
                "summary": "Update item",
                "operationId": "update-item",
                "parameters": [
                    {
                        "type": "integer",
                        "description": "list_id",
                        "name": "list_id",
                        "in": "path",
                        "required": true
                    },
                    {
                        "type": "integer",
                        "description": "item_id",
                        "name": "item_id",
                        "in": "path",
                        "required": true
                    },
                    {
                        "description": "input",
                        "name": "input",
                        "in": "body",
                        "required": true,
                        "schema": {
                            "$ref": "#/definitions/models.UpdateItemReq"
                        }
                    }
                ],
                "responses": {
                    "200": {
                        "description": "success",
                        "schema": {
                            "type": "string"
                        }
                    },
                    "400": {
                        "description": "bad input, auth header errors",
                        "schema": {
                            "$ref": "#/definitions/handler.ErrorResponse"
                        }
                    },
                    "401": {
                        "description": "user is not authorized",
                        "schema": {
                            "$ref": "#/definitions/handler.ErrorResponse"
                        }
                    },
                    "404": {
                        "description": "list not found, item not found",
                        "schema": {
                            "$ref": "#/definitions/handler.ErrorResponse"
                        }
                    },
                    "500": {
                        "description": "internal error",
                        "schema": {
                            "$ref": "#/definitions/handler.ErrorResponse"
                        }
                    }
                }
            }
        },
        "/api/lists/{list_id}/items/{item_id}/done": {
            "patch": {
                "security": [
                    {
                        "ApiKeyAuth": []
                    }
                ],
                "consumes": [
                    "application/json"
                ],
                "produces": [
                    "application/json"
                ],
                "tags": [
                    "items"
                ],
                "summary": "Done item",
                "operationId": "done-item",
                "parameters": [
                    {
                        "type": "integer",
                        "description": "list_id",
                        "name": "list_id",
                        "in": "path",
                        "required": true
                    },
                    {
                        "type": "integer",
                        "description": "item_id",
                        "name": "item_id",
                        "in": "path",
                        "required": true
                    }
                ],
                "responses": {
                    "200": {
                        "description": "success",
                        "schema": {
                            "type": "string"
                        }
                    },
                    "400": {
                        "description": "bad input, auth header errors",
                        "schema": {
                            "$ref": "#/definitions/handler.ErrorResponse"
                        }
                    },
                    "401": {
                        "description": "user is not authorized",
                        "schema": {
                            "$ref": "#/definitions/handler.ErrorResponse"
                        }
                    },
                    "404": {
                        "description": "list not found, item not found",
                        "schema": {
                            "$ref": "#/definitions/handler.ErrorResponse"
                        }
                    },
                    "500": {
                        "description": "internal error",
                        "schema": {
                            "$ref": "#/definitions/handler.ErrorResponse"
                        }
                    }
                }
            }
        },
        "/auth/confirm/{link}": {
            "get": {
                "consumes": [
                    "application/json"
                ],
                "produces": [
                    "application/json"
                ],
                "tags": [
                    "auth"
                ],
                "summary": "Confirm email",
                "operationId": "confirm",
                "parameters": [
                    {
                        "type": "string",
                        "description": "link confirmation",
                        "name": "link",
                        "in": "path",
                        "required": true
                    }
                ],
                "responses": {
                    "200": {
                        "description": "success",
                        "schema": {
                            "type": "string"
                        }
                    },
                    "404": {
                        "description": "page not found",
                        "schema": {
                            "$ref": "#/definitions/handler.ErrorResponse"
                        }
                    },
                    "500": {
                        "description": "internal error",
                        "schema": {
                            "$ref": "#/definitions/handler.ErrorResponse"
                        }
                    }
                }
            }
        },
        "/auth/logout": {
            "get": {
                "security": [
                    {
                        "ApiKeyAuth": []
                    }
                ],
                "consumes": [
                    "application/json"
                ],
                "produces": [
                    "application/json"
                ],
                "tags": [
                    "auth"
                ],
                "summary": "Log out",
                "operationId": "logout",
                "responses": {
                    "200": {
                        "description": "success",
                        "schema": {
                            "type": "string"
                        }
                    },
                    "400": {
                        "description": "auth header errors",
                        "schema": {
                            "$ref": "#/definitions/handler.ErrorResponse"
                        }
                    },
                    "401": {
                        "description": "user unauthorized",
                        "schema": {
                            "$ref": "#/definitions/handler.ErrorResponse"
                        }
                    },
                    "500": {
                        "description": "internal error",
                        "schema": {
                            "$ref": "#/definitions/handler.ErrorResponse"
                        }
                    }
                }
            }
        },
        "/auth/refresh": {
            "post": {
                "consumes": [
                    "application/json"
                ],
                "produces": [
                    "application/json"
                ],
                "tags": [
                    "auth"
                ],
                "summary": "Refresh token",
                "operationId": "refresh-token",
                "parameters": [
                    {
                        "description": "refresh token",
                        "name": "input",
                        "in": "body",
                        "required": true,
                        "schema": {
                            "$ref": "#/definitions/handler.refreshReq"
                        }
                    }
                ],
                "responses": {
                    "200": {
                        "description": "tokens",
                        "schema": {
                            "$ref": "#/definitions/handler.TokensResponse"
                        }
                    },
                    "400": {
                        "description": "bad token",
                        "schema": {
                            "$ref": "#/definitions/handler.ErrorResponse"
                        }
                    },
                    "401": {
                        "description": "user unauthorized",
                        "schema": {
                            "$ref": "#/definitions/handler.ErrorResponse"
                        }
                    },
                    "500": {
                        "description": "internal error",
                        "schema": {
                            "$ref": "#/definitions/handler.ErrorResponse"
                        }
                    }
                }
            }
        },
        "/auth/sign-in": {
            "post": {
                "consumes": [
                    "application/json"
                ],
                "produces": [
                    "application/json"
                ],
                "tags": [
                    "auth"
                ],
                "summary": "Sign in",
                "operationId": "login",
                "parameters": [
                    {
                        "description": "credentials",
                        "name": "input",
                        "in": "body",
                        "required": true,
                        "schema": {
                            "$ref": "#/definitions/handler.signupReq"
                        }
                    }
                ],
                "responses": {
                    "200": {
                        "description": "tokens",
                        "schema": {
                            "$ref": "#/definitions/handler.TokensResponse"
                        }
                    },
                    "400": {
                        "description": "bad input",
                        "schema": {
                            "$ref": "#/definitions/handler.ErrorResponse"
                        }
                    },
                    "401": {
                        "description": "user not activated",
                        "schema": {
                            "$ref": "#/definitions/handler.ErrorResponse"
                        }
                    },
                    "404": {
                        "description": "user not found",
                        "schema": {
                            "$ref": "#/definitions/handler.ErrorResponse"
                        }
                    },
                    "422": {
                        "description": "max logged in users in one account",
                        "schema": {
                            "$ref": "#/definitions/handler.ErrorResponse"
                        }
                    },
                    "500": {
                        "description": "internal error",
                        "schema": {
                            "$ref": "#/definitions/handler.ErrorResponse"
                        }
                    }
                }
            }
        },
        "/auth/sign-up": {
            "post": {
                "consumes": [
                    "application/json"
                ],
                "produces": [
                    "application/json"
                ],
                "tags": [
                    "auth"
                ],
                "summary": "Sign up",
                "operationId": "register",
                "parameters": [
                    {
                        "description": "register",
                        "name": "input",
                        "in": "body",
                        "required": true,
                        "schema": {
                            "$ref": "#/definitions/handler.signupReq"
                        }
                    }
                ],
                "responses": {
                    "200": {
                        "description": "success",
                        "schema": {
                            "type": "string"
                        }
                    },
                    "400": {
                        "description": "bad input",
                        "schema": {
                            "$ref": "#/definitions/handler.ErrorResponse"
                        }
                    },
                    "409": {
                        "description": "user already exists",
                        "schema": {
                            "$ref": "#/definitions/handler.ErrorResponse"
                        }
                    },
                    "500": {
                        "description": "internal error",
                        "schema": {
                            "$ref": "#/definitions/handler.ErrorResponse"
                        }
                    }
                }
            }
        }
    },
    "definitions": {
        "handler.ErrorResponse": {
            "type": "object",
            "properties": {
                "message": {
                    "type": "string"
                },
                "status": {
                    "type": "string"
                }
            }
        },
        "handler.ItemCreateResponse": {
            "type": "object",
            "properties": {
                "item_id": {
                    "type": "integer"
                },
                "status": {
                    "type": "string"
                }
            }
        },
        "handler.ListCreateResponse": {
            "type": "object",
            "properties": {
                "list_id": {
                    "type": "integer"
                },
                "status": {
                    "type": "string"
                }
            }
        },
        "handler.TokensResponse": {
            "type": "object",
            "properties": {
                "access_token": {
                    "type": "string"
                },
                "refresh_token": {
                    "type": "string"
                }
            }
        },
        "handler.UserItemsResponse": {
            "type": "object",
            "properties": {
                "result": {
                    "type": "array",
                    "items": {
                        "$ref": "#/definitions/models.Item"
                    }
                },
                "status": {
                    "type": "string"
                }
            }
        },
        "handler.UserListsResponse": {
            "type": "object",
            "properties": {
                "result": {
                    "type": "array",
                    "items": {
                        "$ref": "#/definitions/models.List"
                    }
                },
                "status": {
                    "type": "string"
                }
            }
        },
        "handler.editRoleReq": {
            "type": "object",
            "required": [
                "is_admin",
                "user_id"
            ],
            "properties": {
                "is_admin": {
                    "type": "boolean"
                },
                "user_id": {
                    "type": "integer"
                }
            }
        },
        "handler.itemCreateReq": {
            "type": "object",
            "required": [
                "description",
                "title"
            ],
            "properties": {
                "description": {
                    "type": "string"
                },
                "title": {
                    "type": "string"
                }
            }
        },
        "handler.listCreateReq": {
            "type": "object",
            "required": [
                "description",
                "title"
            ],
            "properties": {
                "description": {
                    "type": "string"
                },
                "title": {
                    "type": "string"
                }
            }
        },
        "handler.refreshReq": {
            "type": "object",
            "required": [
                "refresh_token"
            ],
            "properties": {
                "refresh_token": {
                    "type": "string"
                }
            }
        },
        "handler.signupReq": {
            "type": "object",
            "required": [
                "email",
                "password"
            ],
            "properties": {
                "email": {
                    "type": "string"
                },
                "password": {
                    "type": "string"
                }
            }
        },
        "models.Item": {
            "type": "object",
            "properties": {
                "description": {
                    "type": "string"
                },
                "done": {
                    "type": "boolean"
                },
                "id": {
                    "type": "integer"
                },
                "list_id": {
                    "type": "integer"
                },
                "title": {
                    "type": "string"
                }
            }
        },
        "models.List": {
            "type": "object",
            "properties": {
                "description": {
                    "type": "string"
                },
                "list_id": {
                    "type": "integer"
                },
                "title": {
                    "type": "string"
                }
            }
        },
        "models.UpdateItemReq": {
            "type": "object",
            "properties": {
                "description": {
                    "type": "string"
                },
                "title": {
                    "type": "string"
                }
            }
        },
        "models.UpdateListReq": {
            "type": "object",
            "properties": {
                "description": {
                    "type": "string"
                },
                "title": {
                    "type": "string"
                }
            }
        }
    },
    "securityDefinitions": {
        "ApiKeyAuth": {
            "type": "apiKey",
            "name": "Authorization",
            "in": "header"
        }
    }
}